{
  "source": "instagram-public-reel-pages",
  "profile": "https://www.instagram.com/artic.live/",
  "crawledAt": "2026-06-25T16:42:10.202Z",
  "keywords": [
    "실시간",
    "오늘자",
    "어제자"
  ],
  "scanned": 1,
  "directUrls": 1,
  "headless": true,
  "items": [
    {
      "label": "실시간",
      "caption": "실시간 리스닝 파티 끝나고 팬들과 셋로그 찍는 강지원(@kangziwon) Venue @twrecords_seoul Thanks to @gedative @sehooninseoul",
      "fullCaption": "실시간 리스닝 파티 끝나고 팬들과 셋로그 찍는 강지원(@kangziwon) Venue @twrecords_seoul Thanks to @gedative @sehooninseoul",
      "eventTitle": "강지원 'Ordinary Ever After' Listening Session",
      "date": "2026-05-18",
      "year": 2026,
      "quarter": "Q2",
      "issue": "2026 Q2",
      "imageUrl": "/images/quarterly/now-artic/DYhoO-8PAZX.jpg",
      "url": "https://www.instagram.com/artic.live/reel/DYhoO-8PAZX/",
      "source": "Instagram",
      "embedUrl": "https://www.instagram.com/reel/DYhoO-8PAZX/embed/"
    }
  ]
}
